pyimportcyclefinder-0.1.4.dist-info/METADATA
pyimportcyclefinder-0.1.4.dist-info/WHEEL
pyimportcyclefinder-0.1.4.dist-info/entry_points.txt
pyimportcyclefinder-0.1.4.dist-info/licenses/LICENSE
pyimportcyclefinder/__init__.py
pyimportcyclefinder/_version.py
pyimportcyclefinder/cli.py
pyimportcyclefinder/find_cycles.py
pyimportcyclefinder/get_version.py
pyimportcyclefinder/protocol/__init__.py
pyimportcyclefinder/protocol/base/__init__.py
pyimportcyclefinder/protocol/base/re.py
pyimportcyclefinder/protocol/base/regex.py
pyimportcyclefinder/protocol/re.py
pyimportcyclefinder/protocol/regex.py
pyimportcyclefinder/tests/__init__.py
pyimportcyclefinder/tests/fake_test_packages/__init__.py
pyimportcyclefinder/tests/fake_test_packages/simple_cyclic_imports/__init__.py
pyimportcyclefinder/tests/fake_test_packages/simple_cyclic_imports/a_imports_b.py
pyimportcyclefinder/tests/fake_test_packages/simple_cyclic_imports/b_imports_a.py
pyimportcyclefinder/tests/test_cli.py
pyimportcyclefinder/tests/test_cycle_finder.py
pyimportcyclefinder/tests/test_pattern_protocols.py
pyimportcyclefinder/tests/test_scanner_protocols.py
pyimportcyclefinder/tests/test_splitter_protocol.py
pyimportcyclefinder/validator.py
pyimportcyclefinder-0.1.4.dist-info/RECORD
